synapsis/__init__.py
synapsis/py.typed
synapsis/core/__init__.py
synapsis/core/cli.py
synapsis/core/exceptions.py
synapsis/core/hooks.py
synapsis/core/narg.py
synapsis/core/synapsis.py
synapsis/core/synapsis_utils.py
synapsis/core/utils.py
synapsis/synapse/__init__.py
synapsis/synapse/synapse.py
synapsis/synapse/synapse_concrete_type.py
synapsis/synapse/synapse_permission.py
synapsis/synapse/synapse_utils.py
synapsis/synapse/synapse_utils.pyi
synapsis-0.0.9.dist-info/METADATA
synapsis-0.0.9.dist-info/WHEEL
synapsis-0.0.9.dist-info/licenses/LICENSE
synapsis-0.0.9.dist-info/licenses/NOTICE
synapsis-0.0.9.dist-info/RECORD
