Metadata-Version: 2.1
Name: synapsis
Version: 0.0.9
Summary: Synapse integration utilities with asyncio support.
Project-URL: repository, https://github.com/ki-tools/synapsis-py
License:                                  Apache License
License-File: LICENSE
License-File: NOTICE
Keywords: Synapse,asyncio
Classifier: License :: OSI Approved :: Apache Software License
Classifier: Operating System :: OS Independent
Classifier: Programming Language :: Python
Classifier: Programming Language :: Python :: 3.10
Classifier: Programming Language :: Python :: 3.11
Requires-Python: >=3.10
Requires-Dist: dotchain
Requires-Dist: synapseclient<3.0.0,>=2.3.1
